[
  {
    "title": "Accueil",
    "description": "Vues & Sections",
    "icon": "LayoutDashboard",
    "link": "/admin/home",
    "baseColor": "#ff0000",
    "permission": "superadmin",
    "columns": 1,
    "category": "ALL",
    "bg": "bg-neon-cyan/5",
    "color": "border-neon-cyan/20 hover:border-neon-cyan"
  },
  {
    "title": "Social Studio",
    "description": "Vidéos & Stories",
    "icon": "Instagram",
    "link": "social-studio",
    "color": "border-neon-pink/20 hover:border-neon-pink",
    "bg": "bg-neon-pink/5",
    "permission": "social_studio",
    "baseColor": "#ff00d0",
    "columns": 1,
    "category": "STUDIO"
  },
  {
    "title": "Contenu",
    "description": "News, Musique, Interviews...",
    "icon": "FileText",
    "category": "NEWS",
    "link": "#",
    "color": "border-neon-cyan/20 hover:border-neon-cyan",
    "bg": "bg-neon-cyan/5",
    "permission": "news_focus",
    "baseColor": "#a600ff",
    "columns": 1
  },
  {
    "title": "Vérifier Photos",
    "description": "WIKI : Photos en attente",
    "icon": "ShieldAlert",
    "category": "NEWS",
    "link": "#",
    "color": "border-neon-red/20 hover:border-neon-red",
    "bg": "bg-neon-red/5",
    "permission": "wiki_dropsiders",
    "baseColor": "#ff0000",
    "columns": 1
  },
  {
    "title": "Agenda",
    "description": "Gérer les dates",
    "icon": "Calendar",
    "link": "/admin/manage?tab=Agenda",
    "baseColor": "#0400ff",
    "permission": "agenda_events",
    "category": "NEWS",
    "bg": "bg-neon-yellow/5",
    "color": "border-neon-yellow/20 hover:border-neon-yellow",
    "columns": 1
  },
  {
    "title": "Statistiques",
    "description": "Analyse du site",
    "icon": "BarChart3",
    "link": "/admin/stats",
    "baseColor": "#00bfff",
    "permission": "stats_analytics",
    "columns": 1,
    "category": "STUDIO",
    "bg": "bg-neon-cyan/5",
    "color": "border-neon-cyan/20 hover:border-neon-cyan"
  },
  {
    "title": "Shop",
    "description": "Gérer le shop",
    "icon": "ShoppingBag",
    "link": "/admin/shop",
    "baseColor": "#00ffcc",
    "permission": "shop",
    "category": "SHOP",
    "bg": "bg-neon-pink/5",
    "color": "border-neon-pink/20 hover:border-neon-pink"
  },
  {
    "title": "Spotify",
    "description": "Playlists accueil",
    "icon": "Music",
    "link": "/admin/spotify",
    "baseColor": "#1eff00",
    "permission": "musique_releases",
    "columns": 1,
    "category": "STUDIO",
    "bg": "bg-neon-green/5",
    "color": "border-neon-green/20 hover:border-neon-green"
  },
  {
    "title": "Newsletter",
    "description": "Studio de création",
    "icon": "Mail",
    "link": "/newsletter/studio",
    "baseColor": "#fbff00",
    "permission": "push_newsletter",
    "columns": 1,
    "category": "SHOP",
    "bg": "bg-green-400/5",
    "color": "border-green-400/20 hover:border-green-400"
  },
  {
    "title": "Quiz & Blind Test",
    "description": "Questions & Musique",
    "icon": "Gamepad2",
    "category": "CONCOURS",
    "link": "#",
    "color": "border-neon-red/20 hover:border-neon-red",
    "bg": "bg-neon-red/5",
    "permission": "community_mod",
    "baseColor": "#ffa200",
    "columns": 1
  },
  {
    "title": "Concours Insta",
    "description": "Participants Instagram",
    "icon": "Instagram",
    "category": "CONCOURS",
    "link": "#",
    "color": "border-neon-pink/20 hover:border-neon-pink",
    "bg": "bg-neon-pink/5",
    "permission": "community_mod",
    "baseColor": "#ff4d00",
    "columns": 1
  },
  {
    "title": "L'Équipe & Éditeurs",
    "description": "Accès & Membres",
    "icon": "Users",
    "category": "TEAM",
    "link": "#",
    "color": "border-neon-purple/20 hover:border-neon-purple",
    "bg": "bg-neon-purple/5",
    "permission": "all",
    "baseColor": "#ff0000",
    "columns": 1
  },
  {
    "title": "Messagerie",
    "description": "Emails & Contact",
    "icon": "Mail",
    "category": "SHOP",
    "link": "#",
    "color": "border-neon-orange/20 hover:border-neon-orange",
    "bg": "bg-neon-orange/5",
    "permission": "messages_contact",
    "baseColor": "#ffffff",
    "columns": 1
  },
  {
    "title": "Tracklists",
    "description": "Vérifier & Valider",
    "icon": "Music",
    "category": "STUDIO",
    "link": "#",
    "color": "border-neon-purple/20 hover:border-neon-purple",
    "bg": "bg-neon-purple/5",
    "permission": "musique_releases",
    "baseColor": "#00357a",
    "columns": 1
  },
  {
    "title": "Downloader",
    "description": "Outil Médias",
    "icon": "Download",
    "category": "STUDIO",
    "link": "#",
    "color": "border-neon-cyan/20 hover:border-neon-cyan",
    "bg": "bg-neon-cyan/5",
    "permission": "all",
    "baseColor": "#00f0ff",
    "columns": 1
  },
  {
    "title": "Notifications",
    "description": "Push News",
    "icon": "Bell",
    "category": "SHOP",
    "link": "#",
    "color": "border-neon-yellow/20 hover:border-neon-yellow",
    "bg": "bg-neon-yellow/5",
    "permission": "push_newsletter",
    "baseColor": "#fbff00",
    "columns": 1
  },
  {
    "title": "Communauté",
    "description": "Commentaires & Membres",
    "icon": "MessageSquare",
    "category": "CONCOURS",
    "link": "#",
    "color": "border-neon-pink/20 hover:border-neon-pink",
    "bg": "bg-neon-pink/5",
    "permission": "community_mod",
    "baseColor": "#ff00d0",
    "columns": 1
  }
]